setup.py
./rfclient/__init__.py
./rfclient/redflash.py
./rfclient/rflogger.py
rfclient.egg-info/PKG-INFO
rfclient.egg-info/SOURCES.txt
rfclient.egg-info/dependency_links.txt
rfclient.egg-info/top_level.txt