Metadata-Version: 1.1
Name: rfclient
Version: 0.2.3
Summary: API to the RedFlash notification management system.
Home-page: https://github.com/aquamatt/rfclient
Author: ReThought Ltd
Author-email: code@rethought-solutions.com
License: BSD
Keywords: api
Platform: UNKNOWN
Classifier: Intended Audience :: Developers
Classifier: License :: OSI Approved :: BSD License
Classifier: Operating System :: OS Independent
Classifier: Programming Language :: Python
